causal_sampler/__init__.py
causal_sampler/gmmSampler.py
causal_sampler/pipeline.py
causal_sampler/utils.py
causal_sampler-0.0.5.dist-info/licenses/LICENSE
causal_sampler-0.0.5.dist-info/METADATA
causal_sampler-0.0.5.dist-info/WHEEL
causal_sampler-0.0.5.dist-info/top_level.txt
causal_sampler-0.0.5.dist-info/RECORD
